obmpy/__init__.py
obmpy/__main__.py
obmpy/cli.py
obmpy/files.py
obmpy/pyboard.py
openblock_obmpy-1.3.5.dist-info/LICENSE
openblock_obmpy-1.3.5.dist-info/METADATA
openblock_obmpy-1.3.5.dist-info/WHEEL
openblock_obmpy-1.3.5.dist-info/entry_points.txt
openblock_obmpy-1.3.5.dist-info/top_level.txt
openblock_obmpy-1.3.5.dist-info/RECORD
