Metadata-Version: 2.1
Name: openblock-obmpy
Version: 1.3.5
Summary: obmpy (OpenBlock MicroPython tool) is a command line tool to interact with a CircuitPython or MicroPython board over a serial connection.
Home-page: https://github.com/openblock/obmpy
Author: OpenBlock Team
Author-email: arthurzheng@openblock.cc
License: MIT
Keywords: openblock obmpy hardware micropython circuitpython
Platform: UNKNOWN
Classifier: Development Status :: 4 - Beta
Classifier: Intended Audience :: Developers
Classifier: License :: OSI Approved :: MIT License
Classifier: Programming Language :: Python :: 2
Classifier: Programming Language :: Python :: 2.6
Classifier: Programming Language :: Python :: 2.7
Classifier: Programming Language :: Python :: 3
Classifier: Programming Language :: Python :: 3.3
Classifier: Programming Language :: Python :: 3.4
Classifier: Programming Language :: Python :: 3.5
License-File: LICENSE
